optim_sowingdate/__init__.py
optim_sowingdate/analysis.py
optim_sowingdate/cmd.py
optim_sowingdate/optimizer.py
optim_sowingdate-2.6.0.dist-info/LICENSE.txt
optim_sowingdate-2.6.0.dist-info/METADATA
optim_sowingdate-2.6.0.dist-info/WHEEL
optim_sowingdate-2.6.0.dist-info/entry_points.txt
optim_sowingdate-2.6.0.dist-info/top_level.txt
optim_sowingdate-2.6.0.dist-info/RECORD
